encoding_tools/__init__.py
encoding_tools/constants.py
encoding_tools/exceptions.py
encoding_tools/helpers.py
encoding_tools-0.0.3.dist-info/METADATA
encoding_tools-0.0.3.dist-info/RECORD
encoding_tools-0.0.3.dist-info/WHEEL
encoding_tools-0.0.3.dist-info/top_level.txt
