Metadata-Version: 2.1
Name: encoding-tools
Version: 0.0.3
Summary: A package to deal with encoding.
Home-page: https://github.com/Tberdy/encoding_tools
Author: Thomas Berdy
Author-email: thomas.berdy@outlook.com
License: UNKNOWN
Platform: UNKNOWN
Classifier: Programming Language :: Python :: 3
Classifier: License :: OSI Approved :: MIT License
Classifier: Operating System :: OS Independent
Classifier: Topic :: Text Processing :: Linguistic
Classifier: Topic :: Software Development :: Libraries :: Python Modules
Requires-Dist: chardet
Requires-Dist: Unidecode
